CHANGES.rst
COPYRIGHT.rst
DEVELOPMENT.rst
LICENSE.rst
MANIFEST.in
README.rst
bootstrap.py
buildout.cfg
setup.py
tox.ini
src/z3c/__init__.py
src/z3c.testsetup.egg-info/PKG-INFO
src/z3c.testsetup.egg-info/SOURCES.txt
src/z3c.testsetup.egg-info/dependency_links.txt
src/z3c.testsetup.egg-info/namespace_packages.txt
src/z3c.testsetup.egg-info/not-zip-safe
src/z3c.testsetup.egg-info/requires.txt
src/z3c.testsetup.egg-info/top_level.txt
src/z3c/testsetup/HOWTO_UPGRADE.txt
src/z3c/testsetup/README.txt
src/z3c/testsetup/__init__.py
src/z3c/testsetup/base.py
src/z3c/testsetup/basicsetup.txt
src/z3c/testsetup/doctesting.py
src/z3c/testsetup/pythontestsetup.txt
src/z3c/testsetup/testgetter.py
src/z3c/testsetup/testgetter.txt
src/z3c/testsetup/testing.py
src/z3c/testsetup/testrunner.py
src/z3c/testsetup/testrunner.txt
src/z3c/testsetup/unitdoctestsetup.txt
src/z3c/testsetup/unittestsetup.txt
src/z3c/testsetup/util.py
src/z3c/testsetup/util.txt
src/z3c/testsetup/functional/__init__.py
src/z3c/testsetup/functional/doctesting.py
src/z3c/testsetup/functional/ftesting.zcml
src/z3c/testsetup/functional/functionaldoctestsetup.txt
src/z3c/testsetup/functional/layer.py
src/z3c/testsetup/functional/testgetter.py
src/z3c/testsetup/tests/README_OLD.txt
src/z3c/testsetup/tests/__init__.py
src/z3c/testsetup/tests/setupininit.txt
src/z3c/testsetup/tests/setupininit_nonfunctional.txt
src/z3c/testsetup/tests/test_base.py
src/z3c/testsetup/tests/test_nozopeapptesting.py
src/z3c/testsetup/tests/test_samples.py
src/z3c/testsetup/tests/test_testgetter.py
src/z3c/testsetup/tests/test_testsetup.py
src/z3c/testsetup/tests/test_util.py
src/z3c/testsetup/tests/util.txt
src/z3c/testsetup/tests/cave/.hiddenfile.txt
src/z3c/testsetup/tests/cave/__init__.py
src/z3c/testsetup/tests/cave/broken_mod.py
src/z3c/testsetup/tests/cave/checkertest.chk
src/z3c/testsetup/tests/cave/file1.py
src/z3c/testsetup/tests/cave/file1.rst
src/z3c/testsetup/tests/cave/file1.txt
src/z3c/testsetup/tests/cave/file2.TXT
src/z3c/testsetup/tests/cave/globstest.chk
src/z3c/testsetup/tests/cave/notatest1.foo
src/z3c/testsetup/tests/cave/notatest2.py
src/z3c/testsetup/tests/cave/sampleftesting.zcml
src/z3c/testsetup/tests/cave/samplesetup1.py
src/z3c/testsetup/tests/cave/samplesetup2.py
