Metadata-Version: 1.1
Name: z3c.testsetup
Version: 0.8.4
Summary: Easier test setup for Zope 3 projects and other Python packages.
Home-page: http://pypi.python.org/pypi/z3c.testsetup
Author: Zope Foundation and Contributors
Author-email: zope-dev@zope.org
License: ZPL 2.1
Keywords: zope3 zope tests unittest doctest testsetup
Platform: UNKNOWN
Classifier: Development Status :: 3 - Alpha
Classifier: Environment :: Web Environment
Classifier: Intended Audience :: Developers
Classifier: License :: OSI Approved :: Zope Public License
Classifier: Programming Language :: Python
Classifier: Programming Language :: Python :: 2
Classifier: Programming Language :: Python :: 2.6
Classifier: Programming Language :: Python :: 2.7
Classifier: Programming Language :: Python :: 3
Classifier: Programming Language :: Python :: 3.3
Classifier: Programming Language :: Python :: 3.4
Classifier: Programming Language :: Python :: Implementation :: CPython
Classifier: Programming Language :: Python :: Implementation :: PyPy
Classifier: Operating System :: OS Independent
Classifier: Framework :: Zope3
